enigma/__init__.py
enigma/client.py
enigma_io-0.1.1.dist-info/DESCRIPTION.rst
enigma_io-0.1.1.dist-info/entry_points.txt
enigma_io-0.1.1.dist-info/METADATA
enigma_io-0.1.1.dist-info/metadata.json
enigma_io-0.1.1.dist-info/RECORD
enigma_io-0.1.1.dist-info/top_level.txt
enigma_io-0.1.1.dist-info/WHEEL
