Metadata-Version: 2.0
Name: enigma-io
Version: 0.1.1
Summary: enigma-io is a Python Client for the Enigma V2 API
Home-page: https://github.com/talwai/py-enigma
Author: Aaditya Talwai
Author-email: aaditya.21@gmail.com
License: MIT
Keywords: enigma enigma.io python client
Platform: UNKNOWN
Classifier: Development Status :: 3 - Alpha
Classifier: Intended Audience :: Developers
Classifier: Topic :: Software Development
Classifier: License :: OSI Approved :: MIT License
Classifier: Programming Language :: Python :: 2
Classifier: Programming Language :: Python :: 2.6
Classifier: Programming Language :: Python :: 2.7
Classifier: Programming Language :: Python :: 3
Classifier: Programming Language :: Python :: 3.2
Classifier: Programming Language :: Python :: 3.3
Classifier: Programming Language :: Python :: 3.4
Requires-Dist: requests (==2.7.0)
Provides-Extra: test
Requires-Dist: nose (==1.3.7); extra == 'test'
Requires-Dist: tox; extra == 'test'
